Workbook

Sheet Assumptions
A1: Operations Forecasting & Optimisation Model
A2: Meshack Offei-Essah | Nottingham Trent University | 2025
A3: Informed by hands-on event operations experience — including logistics coordination, budget tracking, and supplier management — applied here to model operational efficiency gains in a scalable business context.
A5: KEY MODEL ASSUMPTIONS
A6: Assumption | B6: Value | C6: Notes / Source
A7: Revenue Growth Rate | B7: 0.15 | C7: 15% YoY growth; benchmarked against SME sector averages
A8: Cost Reduction Target | B8: 0.2 | C8: 20% reduction via process optimisation (lean methodology)
A9: Base Units / Volume | B9: 10000 | C9: Annual operational units (e.g. event bookings / transactions)
A10: Price per Unit (£) | B10: 50 | C10: Blended average revenue per unit
A11: Base Cost per Unit (£) | B11: 30 | C11: Fully-loaded cost per unit at Year 0
A14: Yellow = editable input (change me) | B14: Blue text = hardcoded assumption

Sheet 3-Year Forecast
A1: 3-Year Operations Forecast
A2: Meshack Offei-Essah | NTU 2025 | All figures in £
A4: Metric | B4: Year 0 (Base) | C4: Year 1 | D4: Year 2 | E4: Year 3
A5: Units / Volume | B5: =Assumptions!B9 -> 10000 | C5: =B5*(1+Assumptions!B7) -> 11500 | D5: =C5*(1+Assumptions!B7) -> 13225 | E5: =D5*(1+Assumptions!B7) -> 15208.75
A6: Price per Unit (£) | B6: =Assumptions!B10 -> 50 | C6: =B6 -> 50 | D6: =C6 -> 50 | E6: =D6 -> 50
A7: Revenue (£) | B7: =B5*B6 -> 500000 | C7: =C5*C6 -> 575000 | D7: =D5*D6 -> 661250 | E7: =E5*E6 -> 760437.5
A8: Cost per Unit (£) | B8: =Assumptions!B11 -> 30 | C8: =B8*(1-Assumptions!B8) -> 24 | D8: =C8 -> 24 | E8: =D8 -> 24
A9: Total Costs (£) | B9: =B5*B8 -> 300000 | C9: =C5*C8 -> 276000 | D9: =D5*D8 -> 317400 | E9: =E5*E8 -> 365010
A10: Efficiency Gain (£) | B10: 0 | C10: =B9-C9 -> 24000 | D10: =B9-D9 -> -17400 | E10: =B9-E9 -> -65010
A11: Gross Profit (£) | B11: =B7-B9 -> 200000 | C11: =C7-C9 -> 299000 | D11: =D7-D9 -> 343850 | E11: =E7-E9 -> 395427.5
A12: Margin % | B12: =IFERROR(B11/B7,0) -> 0.4 | C12: =IFERROR(C11/C7,0) -> 0.52 | D12: =IFERROR(D11/D7,0) -> 0.52 | E12: =IFERROR(E11/E7,0) -> 0.52
A14: Revenue & Efficiency Gain — 3-Year Trend
B15: Year 0 | C15: Year 1 | D15: Year 2 | E15: Year 3
A16: Revenue (£) | B16: =B7 -> 500000 | C16: =C7 -> 575000 | D16: =D7 -> 661250 | E16: =E7 -> 760437.5
A17: Efficiency Gain (£) | B17: =B10 -> 0 | C17: =C10 -> 24000 | D17: =D10 -> -17400 | E17: =E10 -> -65010

Sheet Summary
A1: Executive Summary — Operations Forecasting & Optimisation Model
A2: Meshack Offei-Essah | NTU Business & Finance | President, Finance Society | 2025
A4: KEY INSIGHTS
A5: ✦ | B5: Identified a 20% cost optimisation opportunity through process improvement, reducing cost per unit from £30 to £24 in Year 1. | C5: ='3-Year Forecast'!C10 -> 24000
A6: ✦ | B6: Projected £60,000+ efficiency gain in Year 1 alone — rising to £90,000+ by Year 3 as volume scales with 15% annual growth. | C6: ='3-Year Forecast'!E10 -> -65010
A7: ✦ | B7: Revenue forecast to grow from £500,000 (Year 0) to £760,000+ by Year 3, driven by compounding volume growth at a fixed price point. | C7: ='3-Year Forecast'!E7 -> 760437.5
A8: ✦ | B8: Gross margin expands from 40% (Year 0) to 52%+ by Year 3, demonstrating the leverage of operational efficiency on profitability. | C8: ='3-Year Forecast'!E12 -> 0.52
A9: ✦ | B9: Model structure mirrors real event operations logic: fixed price, variable volume, and controllable cost — directly applicable to budget management in live events.
A11: RECOMMENDATIONS FOR OPERATIONAL TEAMS
A12: 1. | B12: Implement lean process review in Year 1 targeting the 20% cost reduction — prioritise highest-volume operational steps first for maximum savings impact.
A13: 2. | B13: Maintain price per unit at £50 through Year 3; margin expansion is driven by cost discipline, not pricing power — avoid discounting.
A14: 3. | B14: Track efficiency gain (£) monthly against the forecast baseline; use variance analysis to flag operational overspend early.
A15: 4. | B15: Present this model in stakeholder reporting to demonstrate financial literacy and data-driven decision-making to senior leadership.
A17: Model built for academic & professional portfolio use. Assumptions sourced from SME sector benchmarks and event operations experience. © Meshack Offei-Essah, NTU 2025.
